rascal/__init__.py
rascal/atlas.py
rascal/calibrator.py
rascal/houghtransform.py
rascal/models.py
rascal/plotting.py
rascal/synthetic.py
rascal/util.py
rascal/arc_lines/all_nist.csv
rascal/arc_lines/ar.csv
rascal/arc_lines/convolve_lines.py
rascal/arc_lines/cu.csv
rascal/arc_lines/cuar.csv
rascal/arc_lines/cuar_unknown.csv
rascal/arc_lines/cunear_high.csv
rascal/arc_lines/cunear_low.csv
rascal/arc_lines/efosc.csv
rascal/arc_lines/he.csv
rascal/arc_lines/hg.csv
rascal/arc_lines/kr.csv
rascal/arc_lines/ne.csv
rascal/arc_lines/nist_clean.csv
rascal/arc_lines/xe.csv
rascal/arc_lines/xe_strong.csv
rascal-0.3.10.dist-info/LICENSE
rascal-0.3.10.dist-info/METADATA
rascal-0.3.10.dist-info/WHEEL
rascal-0.3.10.dist-info/top_level.txt
rascal-0.3.10.dist-info/RECORD
