Metadata-Version: 2.1
Name: rascal
Version: 0.3.10
Summary: The Pyhton Automated Wavelenmgth Calibrator.
Home-page: https://rascal.readthedocs.io/en/latest/?badge=latest
Download-URL: https://github.com/jveitchmichaelis/rascal
Author: Josh Veitch-Michaelis, Marco C Lam
Author-email: j.veitchmichaelis@gmail.com, lam@mail.tau.ac.il
Maintainer: Josh Veitch-Michaelis, Marco C Lam
Maintainer-email: j.veitchmichaelis@gmail.com, lam@mail.tau.ac.il
License: BSD-3-Clause
Classifier: License :: OSI Approved :: BSD License
Classifier: Programming Language :: Python :: 3
Classifier: Programming Language :: Python :: 3.7
Classifier: Programming Language :: Python :: 3.8
Classifier: Programming Language :: Python :: 3.9
Classifier: Programming Language :: Python :: 3.10
Classifier: Programming Language :: Python :: 3.11
Classifier: Operating System :: OS Independent
Requires-Python: >=3.6
License-File: LICENSE
Requires-Dist: numpy (<1.24,>=1.16)
Requires-Dist: scipy (>=1.3.3)
Requires-Dist: pynverse (>=0.1.4)
Requires-Dist: matplotlib (>=3.0.3)
Requires-Dist: tqdm (>=4.48.0)
